gnc/__init__.py
gnc/_gnc.pyd
gnc/corr_tracker.py
gnc/opencv_world4100.dll
gnc-1.0.2.dist-info/METADATA
gnc-1.0.2.dist-info/WHEEL
gnc-1.0.2.dist-info/top_level.txt
gnc-1.0.2.dist-info/RECORD
