Metadata-Version: 2.2
Name: gnc
Version: 1.0.2
Summary: Custom Correlation tracker.
Home-page: https://github.com/kolesnikdi/corr_tracker
Author: Oleksii Hospodarchuk; Denys Kolesnyk
Author-email: olexago@ukr.net; kolesnik.d.i@gmail.com
Classifier: Programming Language :: Python :: 3.12
Classifier: Programming Language :: C++
Classifier: License :: OSI Approved :: MIT License
Classifier: Operating System :: Microsoft :: Windows
Requires-Python: ==3.12.*
Requires-Dist: opencv-python==4.10.0.84
Requires-Dist: numpy==1.26.4
Requires-Dist: setuptools>=76.0.0
Dynamic: author
Dynamic: author-email
Dynamic: classifier
Dynamic: home-page
Dynamic: requires-dist
Dynamic: requires-python
Dynamic: summary
